setup.cfg
setup.py
dispositor/chain.py
dispositor/example.py
dispositor/planet.py
dispositor/segment.py
dispositor/space.py
dispositor.egg-info/PKG-INFO
dispositor.egg-info/SOURCES.txt
dispositor.egg-info/dependency_links.txt
dispositor.egg-info/not-zip-safe
dispositor.egg-info/top_level.txt
dispositor/db/connection.py
dispositor/db/db.py
dispositor/experiments/degree_of_displacement/degree_of_displacement.py
dispositor/experiments/degree_of_displacement/degree_of_displacement_db.py
dispositor/segment36/main.py