Metadata-Version: 2.1
Name: dispositor
Version: 2.1
Summary: Added the offset degree experiment
Home-page: UNKNOWN
Author-email: astro.slfd@gmail.com
License: UNKNOWN
Platform: UNKNOWN
